combat/__init__.py
combat/exceptions.py
combat/pycombat.py
combat/test_unit.py
combat-0.3.2.dist-info/COPYING
combat-0.3.2.dist-info/LICENSE
combat-0.3.2.dist-info/METADATA
combat-0.3.2.dist-info/WHEEL
combat-0.3.2.dist-info/top_level.txt
combat-0.3.2.dist-info/RECORD
