Metadata-Version: 2.1
Name: combat
Version: 0.3.2
Summary: pyComBat, a Python tool for batch effects correction in high-throughput molecular data using empirical Bayes methods
Home-page: https://github.com/epigenelabs/pyComBat
Author: Abdelkader Behdenna
Author-email: abdelkader@epigenelabs.com
Classifier: Programming Language :: Python :: 3
Classifier: License :: OSI Approved :: GNU General Public License v3 or later (GPLv3+)
Classifier: Operating System :: OS Independent
Requires-Python: >=3.6
License-File: LICENSE
License-File: COPYING
Requires-Dist: numpy (<=1.19.5,>=1.18.5)
Requires-Dist: mpmath (>=1.1.0)
Requires-Dist: pandas (<=1.1.5,>=0.24.2)
Requires-Dist: patsy (==0.5.1)
